{
    "type": "PullRequest",
    "pull": [
        {
            "type": "pull",
            "order": 1,
            "from":"India",
            "to": "UAE",
            "country": "India",
            "city": "Chennai",
            "lat": "10.694385",
            "long": "106.735454"
        },
        {
            "text": "UAE",
            "size": 1.0,
            "country": "India",
            "city": "Delhi",
            "lat": "25.216407",
            "long": "55.264813"
        }
    ]
}